jupytercad_openvsp/__init__.py
jupytercad_openvsp/_version.py
jupytercad_openvsp/handlers.py
jupytercad_openvsp/loader.py
jupytercad_openvsp/vsp3_ydoc.py
jupytercad_openvsp-1.0.0.data/data/etc/jupyter/jupyter_server_config.d/jupytercad_openvsp.json
jupytercad_openvsp-1.0.0.data/data/share/jupyter/labextensions/@jupytercad/jupytercad-openvsp/package.json
jupytercad_openvsp-1.0.0.data/data/share/jupyter/labextensions/@jupytercad/jupytercad-openvsp/static/203.19d5a604e2843d71897b.js
jupytercad_openvsp-1.0.0.data/data/share/jupyter/labextensions/@jupytercad/jupytercad-openvsp/static/728.bafe5ce1b8798dd00671.js
jupytercad_openvsp-1.0.0.data/data/share/jupyter/labextensions/@jupytercad/jupytercad-openvsp/static/remoteEntry.953c3d95aca5e5fa4a86.js
jupytercad_openvsp-1.0.0.data/data/share/jupyter/labextensions/@jupytercad/jupytercad-openvsp/static/style.js
jupytercad_openvsp-1.0.0.data/data/share/jupyter/labextensions/@jupytercad/jupytercad-openvsp/static/third-party-licenses.json
jupytercad_openvsp-1.0.0.data/data/share/jupyter/labextensions/@jupytercad/jupytercad-openvsp/install.json
jupytercad_openvsp-1.0.0.dist-info/METADATA
jupytercad_openvsp-1.0.0.dist-info/WHEEL
jupytercad_openvsp-1.0.0.dist-info/entry_points.txt
jupytercad_openvsp-1.0.0.dist-info/licenses/LICENSE
jupytercad_openvsp-1.0.0.dist-info/RECORD
