Metadata-Version: 2.3
Name: jupytercad_openvsp
Version: 1.0.0
Dynamic: Keywords
Summary: A JupyterCAD extension for OpenVSP
Project-URL: Homepage, https://github.com/jupytercad/JupyterCAD-OpenVSP
Project-URL: Bug Tracker, https://github.com/jupytercad/JupyterCAD-OpenVSP/issues
Project-URL: Repository, https://github.com/jupytercad/JupyterCAD-OpenVSP.git
Author: JupyterCAD contributors
License: BSD 3-Clause License
Classifier: Framework :: Jupyter
Classifier: Framework :: Jupyter :: JupyterLab
Classifier: Framework :: Jupyter :: JupyterLab :: 4
Classifier: Framework :: Jupyter :: JupyterLab :: Extensions
Classifier: Framework :: Jupyter :: JupyterLab :: Extensions :: Prebuilt
Classifier: License :: OSI Approved :: BSD License
Classifier: Programming Language :: Python
Classifier: Programming Language :: Python :: 3
Classifier: Programming Language :: Python :: 3.8
Classifier: Programming Language :: Python :: 3.9
Classifier: Programming Language :: Python :: 3.10
Classifier: Programming Language :: Python :: 3.11
Classifier: Programming Language :: Python :: 3.12
Requires-Python: >=3.8
Requires-Dist: jupyter-server<3,>=2.0.1
Requires-Dist: jupytercad-core<4,>=3.0.0
Requires-Dist: jupytercad-lab<4,>=3.0.0
